FPGA/MAC.sv
module MAC #(
    parameter WIDTH = 16 // Q5.10 = 1 sign + 5 int + 10 frac
)(
    input  logic clk,
    input  logic rst,
    input  logic start,
    input  logic signed [WIDTH-1:0] a,
    input  logic signed [WIDTH-1:0] b,
    input  logic signed [2*WIDTH-1:0] acc_in,
    output logic signed [2*WIDTH-1:0] acc_out,
    output logic valid  // Indicates acc_out is valid
);

    // Stage 1: Latch inputs
    logic signed [WIDTH-1:0] a_reg, b_reg;
    logic signed [2*WIDTH-1:0] acc_reg;
    logic stage1_valid;

    // Stage 2: Multiply
    logic signed [2*WIDTH-1:0] mult_result;
    logic signed [2*WIDTH-1:0] acc_stage2;
    logic stage2_valid;

    // Stage 3: Add and shift
    logic signed [2*WIDTH-1:0] result;
    logic stage3_valid;

    // Pipeline registers
    always_ff @(posedge clk or posedge rst) begin
        if (rst) begin
            a_reg         <= '0;
            b_reg         <= '0;
            acc_reg       <= '0;
            stage1_valid  <= 0;

            mult_result   <= '0;
            acc_stage2    <= '0;
            stage2_valid  <= 0;

            result        <= '0;
            acc_out       <= '0;
            valid         <= 0;
        end else begin
            // Stage 1
            if (start) begin
                a_reg        <= a;
                b_reg        <= b;
                acc_reg      <= acc_in;
                stage1_valid <= 1;
            end else begin
                stage1_valid <= 0;
            end

            // Stage 2
            mult_result   <= a_reg * b_reg;
            acc_stage2    <= acc_reg;
            stage2_valid  <= stage1_valid;

            // Stage 3
            result        <= acc_stage2 + (mult_result >>> 10); // align Q5.10
            stage3_valid  <= stage2_valid;

            // Output
            acc_out <= result;
            valid   <= stage3_valid;
        end
    end

endmodule

`timescale 1ns/1ps

module tb_mac_unit;

    parameter WIDTH = 16;

    logic clk;
    logic rst;
    logic start;
    logic signed [WIDTH-1:0] a, b;
    logic signed [2*WIDTH-1:0] acc_in;
    logic signed [2*WIDTH-1:0] acc_out;
    logic valid;

    // Instantiate the pipelined MAC unit
    MAC #(.WIDTH(WIDTH)) dut (
        .clk(clk),
        .rst(rst),
        .start(start),
        .a(a),
        .b(b),
        .acc_in(acc_in),
        .acc_out(acc_out),
        .valid(valid)
    );

    // Clock generation
    always #5 clk = ~clk;  // 100 MHz clock

    // Helper function: convert floating point to Q5.10 fixed point
    function automatic logic signed [WIDTH-1:0] to_fixed(input real r);
        return $rtoi(r * 1024.0);  // 2^10 = 1024
    endfunction

    // Helper function: convert Q5.10 fixed point to real
    function automatic real from_fixed(input logic signed [WIDTH-1:0] f);
        return f / 1024.0;
    endfunction

    initial begin
        $display("Starting pipelined MAC unit test...");
        clk = 0;
        rst = 1;
        start = 0;
        a = 0;
        b = 0;
        acc_in = 0;

        #20 rst = 0;

        // Input #1
        @(posedge clk);
        a = to_fixed(1.5);
        b = to_fixed(2.0);
        acc_in = 0;
        start = 1;

        @(posedge clk);
        start = 0;

        // Input #2 (back-to-back)
        @(posedge clk);
        a = to_fixed(-0.5);
        b = to_fixed(4.0);
        acc_in = 0;
        start = 1;

        @(posedge clk);
        start = 0;

        // Input #3 (accumulate)
        @(posedge clk);
        a = to_fixed(1.0);
        b = to_fixed(1.0);
        acc_in = to_fixed(3.5); // already in Q5.10
        start = 1;

        @(posedge clk);
        start = 0;

        // Wait for all results
        repeat (10) @(posedge clk);

        $finish;
    end

    // Monitor valid results
    always_ff @(posedge clk) begin
        if (valid) begin
            $display("[%0t ns] Output valid: acc_out = %0f", $time, acc_out / 1024.0);
        end
    end

endmodule

FPGA/rtl/layer_controller.sv
//------------------------------------------------------------------------------
// layer_controller.sv
// Fully-streaming layer inference with external accumulator and correct neuron count update
//------------------------------------------------------------------------------
module layer_controller #(
    parameter ADDR_WIDTH    = 10,
    parameter DATA_WIDTH    = 16,
    parameter VECTOR_LEN    = 16,
    parameter NUM_NEURONS   = 16,
    parameter BRAM_LATENCY  = 3,
    parameter MAC_LATENCY   = 4
)(
    input  logic                        clk,
    input  logic                        rst,
    input  logic                        start,
    output logic                        busy,
    output logic                        done,

    // Token BRAM read interface
    output logic                        token_rd_en,
    output logic [ADDR_WIDTH-1:0]       token_rd_addr,
    input  logic [DATA_WIDTH-1:0]       token_rd_data,

    // Weight BRAM read interface
    output logic                        weight_rd_en,
    output logic [ADDR_WIDTH-1:0]       weight_rd_addr,
    input  logic [DATA_WIDTH-1:0]       weight_rd_data,

    // Result BRAM write interface
    output logic                        result_wr_en,
    output logic [ADDR_WIDTH-1:0]       result_wr_addr,
    output logic signed [2*DATA_WIDTH-1:0] result_wr_data
);
    localparam VECTOR_AW     = $clog2(VECTOR_LEN);
    localparam NEURON_AW     = $clog2(NUM_NEURONS);
    localparam TOTAL_LATENCY = BRAM_LATENCY + MAC_LATENCY;

    // 'done' is asserted when not busy
    assign done = !busy;

    //------------------------------------------------------------------------------
    // Control signals
    logic                        running;
    logic [VECTOR_AW-1:0]        read_cnt;
    logic [NEURON_AW-1:0]        neuron_cnt;
    logic signed [2*DATA_WIDTH-1:0] sum_reg;

    //------------------------------------------------------------------------------
    // BRAM read enable/address and result write address
    assign token_rd_en    = running;
    assign token_rd_addr  = read_cnt;
    assign weight_rd_en   = running;
    assign weight_rd_addr = {neuron_cnt, read_cnt};
    assign result_wr_addr = neuron_cnt;

    //------------------------------------------------------------------------------
    // Running state, read counter, neuron counter, sum register
    always_ff @(posedge clk or posedge rst) begin
        if (rst) begin
            running    <= 1'b0;
            read_cnt   <= '0;
            neuron_cnt <= '0;
            busy       <= 1'b0;
            sum_reg    <= '0;
        end else if (start) begin
            running    <= 1'b1;
            read_cnt   <= '0;
            neuron_cnt <= '0;
            busy       <= 1'b1;
            sum_reg    <= '0;
        end else if (running) begin
            // Advance read counter
            if (read_cnt == VECTOR_LEN-1)
                read_cnt <= '0;
            else
                read_cnt <= read_cnt + 1;

            // On end-of-vector valid, bump neuron or stop
            if (eov_valid) begin
                if (neuron_cnt == NUM_NEURONS-1) begin
                    running <= 1'b0;
                    busy    <= 1'b0;
                end else begin
                    neuron_cnt <= neuron_cnt + 1;
                    sum_reg    <= '0;
                end
            end
        end
    end

    //------------------------------------------------------------------------------
    // Generate mac_start by delaying 'running' through BRAM latency
    logic [BRAM_LATENCY-1:0] start_pipe;
    logic                    mac_start;
    always_ff @(posedge clk or posedge rst) begin
        if (rst)
            start_pipe <= '0;
        else
            start_pipe <= {start_pipe[BRAM_LATENCY-2:0], running};
    end
    assign mac_start = start_pipe[BRAM_LATENCY-1];

    //------------------------------------------------------------------------------
    // Detect end-of-vector event when read_cnt wraps
    logic vector_end_event;
    always_comb begin
        vector_end_event = running && (read_cnt == VECTOR_LEN-1);
    end

    //------------------------------------------------------------------------------
    // Align vector_end_event through pipeline to match MAC.valid
    logic [TOTAL_LATENCY-1:0] eov_pipe;
    always_ff @(posedge clk or posedge rst) begin
        if (rst)
            eov_pipe <= '0;
        else
            eov_pipe <= {eov_pipe[TOTAL_LATENCY-2:0], vector_end_event};
    end
    logic eov_valid;
    assign eov_valid = eov_pipe[TOTAL_LATENCY-1] & mac_valid;

    //------------------------------------------------------------------------------
    // Pipe BRAM outputs directly into MAC inputs
    logic signed [DATA_WIDTH-1:0] token_pipe, weight_pipe;
    always_ff @(posedge clk or posedge rst) begin
        if (rst) begin
            token_pipe  <= '0;
            weight_pipe <= '0;
        end else begin
            token_pipe  <= token_rd_data;
            weight_pipe <= weight_rd_data;
        end
    end

    //------------------------------------------------------------------------------
    // Instantiate your MAC as a pure multiplier
    logic signed [2*DATA_WIDTH-1:0] mac_acc_out;
    logic                            mac_valid;
    MAC #(
        .WIDTH(DATA_WIDTH)
    ) mac_i (
        .clk    (clk),
        .rst    (rst),
        .start  (mac_start),
        .a      (token_pipe),
        .b      (weight_pipe),
        .acc_in (1'b0),  // always zero; we do external sum
        .acc_out(mac_acc_out),
        .valid  (mac_valid)
    );

    //------------------------------------------------------------------------------
    // External accumulation and result write
    always_ff @(posedge clk or posedge rst) begin
        if (rst)
            sum_reg <= '0;
        else if (mac_valid)
            sum_reg <= sum_reg + mac_acc_out;
    end

    assign result_wr_en   = eov_valid;
    assign result_wr_data = sum_reg + mac_acc_out;
endmodule

FPGA/bram_buffer.sv
module bram_buffer #(
    parameter ADDR_WIDTH = 10,  // 1024 words
    parameter DATA_WIDTH = 16
)(
    input  logic clk,
    input  logic rst,

    // Write port
    input  logic                  wr_en,
    input  logic [ADDR_WIDTH-1:0] wr_addr,
    input  logic [DATA_WIDTH-1:0] wr_data,

    // Read port
    input  logic                  rd_en,
    input  logic [ADDR_WIDTH-1:0] rd_addr,
    output logic [DATA_WIDTH-1:0] rd_data
);

    localparam DEPTH = 1 << ADDR_WIDTH;

    logic [DATA_WIDTH-1:0] mem [0:DEPTH-1];

    // Write logic
    always_ff @(posedge clk) begin
        if (wr_en)
            mem[wr_addr] <= wr_data;
    end

    // Read logic (synchronous read)
    always_ff @(posedge clk) begin
        if (rd_en)
            rd_data <= mem[rd_addr];
    end

endmodule

FPGA/rtl/layer_top.sv
module layer_top #(
    parameter ADDR_WIDTH   = 10,
    parameter DATA_WIDTH   = 16,
    parameter VECTOR_LEN   = 16,
    parameter NUM_NEURONS  = 16
)(
    input  logic                      clk,
    input  logic                      rst,
    input  logic                      start,

    // Token memory interface (host writes)
    input  logic                      token_wr_en,
    input  logic [ADDR_WIDTH-1:0]     token_wr_addr,
    input  logic [DATA_WIDTH-1:0]     token_wr_data,

    // Weight memory interface (host writes)
    input  logic                      weight_wr_en,
    input  logic [ADDR_WIDTH-1:0]     weight_wr_addr,
    input  logic [DATA_WIDTH-1:0]     weight_wr_data,

    // Result memory read interface (host reads)
    input  logic                      result_rd_en,
    input  logic [ADDR_WIDTH-1:0]     result_rd_addr,
    output logic [2*DATA_WIDTH-1:0]   result_rd_data,

    output logic busy,
    output logic done
);

    // Internal connections for layer_controller
    logic                            tok_rd_en;
    logic [ADDR_WIDTH-1:0]           tok_rd_addr;
    logic [DATA_WIDTH-1:0]           tok_rd_data;

    logic                            wgt_rd_en;
    logic [ADDR_WIDTH-1:0]           wgt_rd_addr;
    logic [DATA_WIDTH-1:0]           wgt_rd_data;

    logic                            res_wr_en;
    logic [ADDR_WIDTH-1:0]           res_wr_addr;
    logic signed [2*DATA_WIDTH-1:0]  res_wr_data;

    // Instantiate token BRAM
    bram_buffer #(
        .ADDR_WIDTH(ADDR_WIDTH),
        .DATA_WIDTH(DATA_WIDTH)
    ) token_mem (
        .clk    (clk),
        .rst    (rst),
        .wr_en  (token_wr_en),
        .wr_addr(token_wr_addr),
        .wr_data(token_wr_data),
        .rd_en  (tok_rd_en),
        .rd_addr(tok_rd_addr),
        .rd_data(tok_rd_data)
    );

    // Instantiate weight BRAM
    bram_buffer #(
        .ADDR_WIDTH(ADDR_WIDTH),
        .DATA_WIDTH(DATA_WIDTH)
    ) weight_mem (
        .clk    (clk),
        .rst    (rst),
        .wr_en  (weight_wr_en),
        .wr_addr(weight_wr_addr),
        .wr_data(weight_wr_data),
        .rd_en  (wgt_rd_en),
        .rd_addr(wgt_rd_addr),
        .rd_data(wgt_rd_data)
    );

    // Instantiate result BRAM
    bram_buffer #(
        .ADDR_WIDTH(ADDR_WIDTH),
        .DATA_WIDTH(2*DATA_WIDTH)
    ) result_mem (
        .clk    (clk),
        .rst    (rst),
        .wr_en  (res_wr_en),
        .wr_addr(res_wr_addr),
        .wr_data(res_wr_data),
        .rd_en  (result_rd_en),
        .rd_addr(result_rd_addr),
        .rd_data(result_rd_data)
    );

    // Instantiate layer controller
    layer_controller #(
        .ADDR_WIDTH(ADDR_WIDTH),
        .DATA_WIDTH(DATA_WIDTH),
        .VECTOR_LEN(VECTOR_LEN),
        .NUM_NEURONS(NUM_NEURONS),
        .BRAM_LATENCY(),  // BRAM latency
        .MAC_LATENCY()     // MAC latency
    ) u_layer_ctrl (
        .clk           (clk),
        .rst           (rst),
        .start         (start),
        .busy          (busy),
        .token_rd_en     (tok_rd_en),
        .token_rd_addr   (tok_rd_addr),
        .token_rd_data   (tok_rd_data),
        .weight_rd_en     (wgt_rd_en),
        .weight_rd_addr   (wgt_rd_addr),
        .weight_rd_data   (wgt_rd_data),
        .result_wr_en     (res_wr_en),
        .result_wr_addr   (res_wr_addr),
        .result_wr_data   (res_wr_data),
        .done          (done)
    );

endmodule

FPGA/sim/vcd/layer_top_tb.vcd
$version Generated by VerilatedVcd $end
$timescale 1ps $end
 $scope module TOP $end
  $var wire 1 = clk $end
  $var wire 1 > rst $end
  $var wire 1 ? start $end
  $var wire 1 @ token_wr_en $end
  $var wire 10 A token_wr_addr [9:0] $end
  $var wire 16 B token_wr_data [15:0] $end
  $var wire 1 C weight_wr_en $end
  $var wire 10 D weight_wr_addr [9:0] $end
  $var wire 16 E weight_wr_data [15:0] $end
  $var wire 1 F result_rd_en $end
  $var wire 10 G result_rd_addr [9:0] $end
  $var wire 32 H result_rd_data [31:0] $end
  $var wire 1 I busy $end
  $var wire 1 J done $end
  $scope module layer_top $end
   $var wire 32 M ADDR_WIDTH [31:0] $end
   $var wire 32 N DATA_WIDTH [31:0] $end
   $var wire 32 N VECTOR_LEN [31:0] $end
   $var wire 32 N NUM_NEURONS [31:0] $end
   $var wire 1 = clk $end
   $var wire 1 > rst $end
   $var wire 1 ? start $end
   $var wire 1 @ token_wr_en $end
   $var wire 10 A token_wr_addr [9:0] $end
   $var wire 16 B token_wr_data [15:0] $end
   $var wire 1 C weight_wr_en $end
   $var wire 10 D weight_wr_addr [9:0] $end
   $var wire 16 E weight_wr_data [15:0] $end
   $var wire 1 F result_rd_en $end
   $var wire 10 G result_rd_addr [9:0] $end
   $var wire 32 H result_rd_data [31:0] $end
   $var wire 1 I busy $end
   $var wire 1 J done $end
   $var wire 1 6 tok_rd_en $end
   $var wire 10 7 tok_rd_addr [9:0] $end
   $var wire 16 K tok_rd_data [15:0] $end
   $var wire 1 6 wgt_rd_en $end
   $var wire 10 8 wgt_rd_addr [9:0] $end
   $var wire 16 L wgt_rd_data [15:0] $end
   $var wire 1 # res_wr_en $end
   $var wire 10 9 res_wr_addr [9:0] $end
   $var wire 32 $ res_wr_data [31:0] $end
   $scope module result_mem $end
    $var wire 32 M ADDR_WIDTH [31:0] $end
    $var wire 32 O DATA_WIDTH [31:0] $end
    $var wire 1 = clk $end
    $var wire 1 > rst $end
    $var wire 1 # wr_en $end
    $var wire 10 9 wr_addr [9:0] $end
    $var wire 32 $ wr_data [31:0] $end
    $var wire 1 F rd_en $end
    $var wire 10 G rd_addr [9:0] $end
    $var wire 32 H rd_data [31:0] $end
    $var wire 32 P DEPTH [31:0] $end
   $upscope $end
   $scope module token_mem $end
    $var wire 32 M ADDR_WIDTH [31:0] $end
    $var wire 32 N DATA_WIDTH [31:0] $end
    $var wire 1 = clk $end
    $var wire 1 > rst $end
    $var wire 1 @ wr_en $end
    $var wire 10 A wr_addr [9:0] $end
    $var wire 16 B wr_data [15:0] $end
    $var wire 1 6 rd_en $end
    $var wire 10 7 rd_addr [9:0] $end
    $var wire 16 K rd_data [15:0] $end
    $var wire 32 P DEPTH [31:0] $end
   $upscope $end
   $scope module u_layer_ctrl $end
    $var wire 32 M ADDR_WIDTH [31:0] $end
    $var wire 32 N DATA_WIDTH [31:0] $end
    $var wire 32 N VECTOR_LEN [31:0] $end
    $var wire 32 N NUM_NEURONS [31:0] $end
    $var wire 32 Q BRAM_LATENCY [31:0] $end
    $var wire 32 R MAC_LATENCY [31:0] $end
    $var wire 1 = clk $end
    $var wire 1 > rst $end
    $var wire 1 ? start $end
    $var wire 1 I busy $end
    $var wire 1 J done $end
    $var wire 1 6 token_rd_en $end
    $var wire 10 7 token_rd_addr [9:0] $end
    $var wire 16 K token_rd_data [15:0] $end
    $var wire 1 6 weight_rd_en $end
    $var wire 10 8 weight_rd_addr [9:0] $end
    $var wire 16 L weight_rd_data [15:0] $end
    $var wire 1 # result_wr_en $end
    $var wire 10 9 result_wr_addr [9:0] $end
    $var wire 32 $ result_wr_data [31:0] $end
    $var wire 32 R VECTOR_AW [31:0] $end
    $var wire 32 R NEURON_AW [31:0] $end
    $var wire 32 S TOTAL_LATENCY [31:0] $end
    $var wire 1 6 running $end
    $var wire 4 : read_cnt [3:0] $end
    $var wire 4 ; neuron_cnt [3:0] $end
    $var wire 32 % sum_reg [31:0] $end
    $var wire 3 & start_pipe [2:0] $end
    $var wire 1 ' mac_start $end
    $var wire 1 < vector_end_event $end
    $var wire 7 ( eov_pipe [6:0] $end
    $var wire 1 # eov_valid $end
    $var wire 16 ) token_pipe [15:0] $end
    $var wire 16 * weight_pipe [15:0] $end
    $var wire 32 + mac_acc_out [31:0] $end
    $var wire 1 , mac_valid $end
    $scope module mac_i $end
     $var wire 32 N WIDTH [31:0] $end
     $var wire 1 = clk $end
     $var wire 1 > rst $end
     $var wire 1 ' start $end
     $var wire 16 ) a [15:0] $end
     $var wire 16 * b [15:0] $end
     $var wire 32 T acc_in [31:0] $end
     $var wire 32 + acc_out [31:0] $end
     $var wire 1 , valid $end
     $var wire 16 - a_reg [15:0] $end
     $var wire 16 . b_reg [15:0] $end
     $var wire 32 / acc_reg [31:0] $end
     $var wire 1 0 stage1_valid $end
     $var wire 32 1 mult_result [31:0] $end
     $var wire 32 2 acc_stage2 [31:0] $end
     $var wire 1 3 stage2_valid $end
     $var wire 32 4 result [31:0] $end
     $var wire 1 5 stage3_valid $end
    $upscope $end
   $upscope $end
   $scope module weight_mem $end
    $var wire 32 M ADDR_WIDTH [31:0] $end
    $var wire 32 N DATA_WIDTH [31:0] $end
    $var wire 1 = clk $end
    $var wire 1 > rst $end
    $var wire 1 C wr_en $end
    $var wire 10 D wr_addr [9:0] $end
    $var wire 16 E wr_data [15:0] $end
    $var wire 1 6 rd_en $end
    $var wire 10 8 rd_addr [9:0] $end
    $var wire 16 L rd_data [15:0] $end
    $var wire 32 P DEPTH [31:0] $end
   $upscope $end
  $upscope $end
 $upscope $end
$enddefinitions $end


#0
0#
b00000000000000000000000000000000 $
b00000000000000000000000000000000 %
b000 &
0'
b0000000 (
b0000000000000000 )
b0000000000000000 *
b00000000000000000000000000000000 +
0,
b0000000000000000 -
b0000000000000000 .
b00000000000000000000000000000000 /
00
b00000000000000000000000000000000 1
b00000000000000000000000000000000 2
03
b00000000000000000000000000000000 4
05
06
b0000000000 7
b0000000000 8
b0000000000 9
b0000 :
b0000 ;
0<
0=
1>
0?
0@
b0000000000 A
b0000000000000000 B
0C
b0000000000 D
b0000000000000000 E
0F
b0000000000 G
b00000000000000000000000000000000 H
0I
1J
b0000000000000000 K
b0000000000000000 L
b00000000000000000000000000001010 M
b00000000000000000000000000010000 N
b00000000000000000000000000100000 O
b00000000000000000000010000000000 P
b00000000000000000000000000000011 Q
b00000000000000000000000000000100 R
b00000000000000000000000000000111 S
b00000000000000000000000000000000 T
#1
1=
#2
0=
#3
1=
#4
0=
#5
1=
#6
0=
#7
1=
#8
0=
0>
#9
1=
#10
0=
1@
#11
1=
#12
0=
b0000000001 A
b0000010000000000 B
#13
1=
#14
0=
b0000000010 A
b0000100000000000 B
#15
1=
#16
0=
b0000000011 A
b0000110000000000 B
#17
1=
#18
0=
b0000000100 A
b0001000000000000 B
#19
1=
#20
0=
b0000000101 A
b0001010000000000 B
#21
1=
#22
0=
b0000000110 A
b0001100000000000 B
#23
1=
#24
0=
b0000000111 A
b0001110000000000 B
#25
1=
#26
0=
b0000001000 A
b0010000000000000 B
#27
1=
#28
0=
b0000001001 A
b0010010000000000 B
#29
1=
#30
0=
b0000001010 A
b0010100000000000 B
#31
1=
#32
0=
b0000001011 A
b0010110000000000 B
#33
1=
#34
0=
b0000001100 A
b0011000000000000 B
#35
1=
#36
0=
b0000001101 A
b0011010000000000 B
#37
1=
#38
0=
b0000001110 A
b0011100000000000 B
#39
1=
#40
0=
b0000001111 A
b0011110000000000 B
#41
1=
#42
0=
0@
#43
1=
#44
0=
1C
b0001000000000000 E
#45
1=
#46
0=
b0000000001 D
#47
1=
#48
0=
b0000000010 D
#49
1=
#50
0=
b0000000011 D
#51
1=
#52
0=
b0000000100 D
#53
1=
#54
0=
b0000000101 D
#55
1=
#56
0=
b0000000110 D
#57
1=
#58
0=
b0000000111 D
#59
1=
#60
0=
b0000001000 D
#61
1=
#62
0=
b0000001001 D
#63
1=
#64
0=
b0000001010 D
#65
1=
#66
0=
b0000001011 D
#67
1=
#68
0=
b0000001100 D
#69
1=
#70
0=
b0000001101 D
#71
1=
#72
0=
b0000001110 D
#73
1=
#74
0=
b0000001111 D
#75
1=
#76
0=
b0000010000 D
#77
1=
#78
0=
b0000010001 D
#79
1=
#80
0=
b0000010010 D
#81
1=
#82
0=
b0000010011 D
#83
1=
#84
0=
b0000010100 D
#85
1=
#86
0=
b0000010101 D
#87
1=
#88
0=
b0000010110 D
#89
1=
#90
0=
b0000010111 D
#91
1=
#92
0=
b0000011000 D
#93
1=
#94
0=
b0000011001 D
#95
1=
#96
0=
b0000011010 D
#97
1=
#98
0=
b0000011011 D
#99
1=
#100
0=
b0000011100 D
#101
1=
#102
0=
b0000011101 D
#103
1=
#104
0=
b0000011110 D
#105
1=
#106
0=
b0000011111 D
#107
1=
#108
0=
b0000100000 D
#109
1=
#110
0=
b0000100001 D
#111
1=
#112
0=
b0000100010 D
#113
1=
#114
0=
b0000100011 D
#115
1=
#116
0=
b0000100100 D
#117
1=
#118
0=
b0000100101 D
#119
1=
#120
0=
b0000100110 D
#121
1=
#122
0=
b0000100111 D
#123
1=
#124
0=
b0000101000 D
#125
1=
#126
0=
b0000101001 D
#127
1=
#128
0=
b0000101010 D
#129
1=
#130
0=
b0000101011 D
#131
1=
#132
0=
b0000101100 D
#133
1=
#134
0=
b0000101101 D
#135
1=
#136
0=
b0000101110 D
#137
1=
#138
0=
b0000101111 D
#139
1=
#140
0=
b0000110000 D
#141
1=
#142
0=
b0000110001 D
#143
1=
#144
0=
b0000110010 D
#145
1=
#146
0=
b0000110011 D
#147
1=
#148
0=
b0000110100 D
#149
1=
#150
0=
b0000110101 D
#151
1=
#152
0=
b0000110110 D
#153
1=
#154
0=
b0000110111 D
#155
1=
#156
0=
b0000111000 D
#157
1=
#158
0=
b0000111001 D
#159
1=
#160
0=
b0000111010 D
#161
1=
#162
0=
b0000111011 D
#163
1=
#164
0=
b0000111100 D
#165
1=
#166
0=
b0000111101 D
#167
1=
#168
0=
b0000111110 D
#169
1=
#170
0=
b0000111111 D
#171
1=
#172
0=
b0001000000 D
#173
1=
#174
0=
b0001000001 D
#175
1=
#176
0=
b0001000010 D
#177
1=
#178
0=
b0001000011 D
#179
1=
#180
0=
b0001000100 D
#181
1=
#182
0=
b0001000101 D
#183
1=
#184
0=
b0001000110 D
#185
1=
#186
0=
b0001000111 D
#187
1=
#188
0=
b0001001000 D
#189
1=
#190
0=
b0001001001 D
#191
1=
#192
0=
b0001001010 D
#193
1=
#194
0=
b0001001011 D
#195
1=
#196
0=
b0001001100 D
#197
1=
#198
0=
b0001001101 D
#199
1=
#200
0=
b0001001110 D
#201
1=
#202
0=
b0001001111 D
#203
1=
#204
0=
b0001010000 D
#205
1=
#206
0=
b0001010001 D
#207
1=
#208
0=
b0001010010 D
#209
1=
#210
0=
b0001010011 D
#211
1=
#212
0=
b0001010100 D
#213
1=
#214
0=
b0001010101 D
#215
1=
#216
0=
b0001010110 D
#217
1=
#218
0=
b0001010111 D
#219
1=
#220
0=
b0001011000 D
#221
1=
#222
0=
b0001011001 D
#223
1=
#224
0=
b0001011010 D
#225
1=
#226
0=
b0001011011 D
#227
1=
#228
0=
b0001011100 D
#229
1=
#230
0=
b0001011101 D
#231
1=
#232
0=
b0001011110 D
#233
1=
#234
0=
b0001011111 D
#235
1=
#236
0=
b0001100000 D
#237
1=
#238
0=
b0001100001 D
#239
1=
#240
0=
b0001100010 D
#241
1=
#242
0=
b0001100011 D
#243
1=
#244
0=
b0001100100 D
#245
1=
#246
0=
b0001100101 D
#247
1=
#248
0=
b0001100110 D
#249
1=
#250
0=
b0001100111 D
#251
1=
#252
0=
b0001101000 D
#253
1=
#254
0=
b0001101001 D
#255
1=
#256
0=
b0001101010 D
#257
1=
#258
0=
b0001101011 D
#259
1=
#260
0=
b0001101100 D
#261
1=
#262
0=
b0001101101 D
#263
1=
#264
0=
b0001101110 D
#265
1=
#266
0=
b0001101111 D
#267
1=
#268
0=
b0001110000 D
#269
1=
#270
0=
b0001110001 D
#271
1=
#272
0=
b0001110010 D
#273
1=
#274
0=
b0001110011 D
#275
1=
#276
0=
b0001110100 D
#277
1=
#278
0=
b0001110101 D
#279
1=
#280
0=
b0001110110 D
#281
1=
#282
0=
b0001110111 D
#283
1=
#284
0=
b0001111000 D
#285
1=
#286
0=
b0001111001 D
#287
1=
#288
0=
b0001111010 D
#289
1=
#290
0=
b0001111011 D
#291
1=
#292
0=
b0001111100 D
#293
1=
#294
0=
b0001111101 D
#295
1=
#296
0=
b0001111110 D
#297
1=
#298
0=
b0001111111 D
#299
1=
#300
0=
b0010000000 D
#301
1=
#302
0=
b0010000001 D
#303
1=
#304
0=
b0010000010 D
#305
1=
#306
0=
b0010000011 D
#307
1=
#308
0=
b0010000100 D
#309
1=
#310
0=
b0010000101 D
#311
1=
#312
0=
b0010000110 D
#313
1=
#314
0=
b0010000111 D
#315
1=
#316
0=
b0010001000 D
#317
1=
#318
0=
b0010001001 D
#319
1=
#320
0=
b0010001010 D
#321
1=
#322
0=
b0010001011 D
#323
1=
#324
0=
b0010001100 D
#325
1=
#326
0=
b0010001101 D
#327
1=
#328
0=
b0010001110 D
#329
1=
#330
0=
b0010001111 D
#331
1=
#332
0=
b0010010000 D
#333
1=
#334
0=
b0010010001 D
#335
1=
#336
0=
b0010010010 D
#337
1=
#338
0=
b0010010011 D
#339
1=
#340
0=
b0010010100 D
#341
1=
#342
0=
b0010010101 D
#343
1=
#344
0=
b0010010110 D
#345
1=
#346
0=
b0010010111 D
#347
1=
#348
0=
b0010011000 D
#349
1=
#350
0=
b0010011001 D
#351
1=
#352
0=
b0010011010 D
#353
1=
#354
0=
b0010011011 D
#355
1=
#356
0=
b0010011100 D
#357
1=
#358
0=
b0010011101 D
#359
1=
#360
0=
b0010011110 D
#361
1=
#362
0=
b0010011111 D
#363
1=
#364
0=
b0010100000 D
#365
1=
#366
0=
b0010100001 D
#367
1=
#368
0=
b0010100010 D
#369
1=
#370
0=
b0010100011 D
#371
1=
#372
0=
b0010100100 D
#373
1=
#374
0=
b0010100101 D
#375
1=
#376
0=
b0010100110 D
#377
1=
#378
0=
b0010100111 D
#379
1=
#380
0=
b0010101000 D
#381
1=
#382
0=
b0010101001 D
#383
1=
#384
0=
b0010101010 D
#385
1=
#386
0=
b0010101011 D
#387
1=
#388
0=
b0010101100 D
#389
1=
#390
0=
b0010101101 D
#391
1=
#392
0=
b0010101110 D
#393
1=
#394
0=
b0010101111 D
#395
1=
#396
0=
b0010110000 D
#397
1=
#398
0=
b0010110001 D
#399
1=
#400
0=
b0010110010 D
#401
1=
#402
0=
b0010110011 D
#403
1=
#404
0=
b0010110100 D
#405
1=
#406
0=
b0010110101 D
#407
1=
#408
0=
b0010110110 D
#409
1=
#410
0=
b0010110111 D
#411
1=
#412
0=
b0010111000 D
#413
1=
#414
0=
b0010111001 D
#415
1=
#416
0=
b0010111010 D
#417
1=
#418
0=
b0010111011 D
#419
1=
#420
0=
b0010111100 D
#421
1=
#422
0=
b0010111101 D
#423
1=
#424
0=
b0010111110 D
#425
1=
#426
0=
b0010111111 D
#427
1=
#428
0=
b0011000000 D
#429
1=
#430
0=
b0011000001 D
#431
1=
#432
0=
b0011000010 D
#433
1=
#434
0=
b0011000011 D
#435
1=
#436
0=
b0011000100 D
#437
1=
#438
0=
b0011000101 D
#439
1=
#440
0=
b0011000110 D
#441
1=
#442
0=
b0011000111 D
#443
1=
#444
0=
b0011001000 D
#445
1=
#446
0=
b0011001001 D
#447
1=
#448
0=
b0011001010 D
#449
1=
#450
0=
b0011001011 D
#451
1=
#452
0=
b0011001100 D
#453
1=
#454
0=
b0011001101 D
#455
1=
#456
0=
b0011001110 D
#457
1=
#458
0=
b0011001111 D
#459
1=
#460
0=
b0011010000 D
#461
1=
#462
0=
b0011010001 D
#463
1=
#464
0=
b0011010010 D
#465
1=
#466
0=
b0011010011 D
#467
1=
#468
0=
b0011010100 D
#469
1=
#470
0=
b0011010101 D
#471
1=
#472
0=
b0011010110 D
#473
1=
#474
0=
b0011010111 D
#475
1=
#476
0=
b0011011000 D
#477
1=
#478
0=
b0011011001 D
#479
1=
#480
0=
b0011011010 D
#481
1=
#482
0=
b0011011011 D
#483
1=
#484
0=
b0011011100 D
#485
1=
#486
0=
b0011011101 D
#487
1=
#488
0=
b0011011110 D
#489
1=
#490
0=
b0011011111 D
#491
1=
#492
0=
b0011100000 D
#493
1=
#494
0=
b0011100001 D
#495
1=
#496
0=
b0011100010 D
#497
1=
#498
0=
b0011100011 D
#499
1=
#500
0=
b0011100100 D
#501
1=
#502
0=
b0011100101 D
#503
1=
#504
0=
b0011100110 D
#505
1=
#506
0=
b0011100111 D
#507
1=
#508
0=
b0011101000 D
#509
1=
#510
0=
b0011101001 D
#511
1=
#512
0=
b0011101010 D
#513
1=
#514
0=
b0011101011 D
#515
1=
#516
0=
b0011101100 D
#517
1=
#518
0=
b0011101101 D
#519
1=
#520
0=
b0011101110 D
#521
1=
#522
0=
b0011101111 D
#523
1=
#524
0=
b0011110000 D
#525
1=
#526
0=
b0011110001 D
#527
1=
#528
0=
b0011110010 D
#529
1=
#530
0=
b0011110011 D
#531
1=
#532
0=
b0011110100 D
#533
1=
#534
0=
b0011110101 D
#535
1=
#536
0=
b0011110110 D
#537
1=
#538
0=
b0011110111 D
#539
1=
#540
0=
b0011111000 D
#541
1=
#542
0=
b0011111001 D
#543
1=
